src/codificador.v
module codificador (
    input [3:0]E,
    output [2:0]S
);

    assign S[2] = (~E[3] & ~E[2] & ~E[1] & ~E[0]);

    assign S[1] =  ((E[0] & ~E[1] & ~E[3]) | 
                    (E[1] & ~E[2] & ~E[3]) |
                    (~E[0] & E[1] & ~E[2]) |
                    (~E[0] & E[2] & ~E[3]) |
                    (~E[0] & ~E[1] & E[3]) |
                    (~E[1] & ~E[2] & E[3]));

    assign S[0] =  ((~E[3] & ~E[2] & ~E[1] & E[0]) |
                    (~E[3] & ~E[2] & E[1] & ~E[0]) |
                    (~E[3] & E[2] & ~E[1] & ~E[0]) |
                    (~E[3] & E[2] & E[1] & E[0])   |
                    (E[3] & ~E[2] & ~E[1] & ~E[0]) |
                    (E[3] & ~E[2] & E[1] & E[0])   |
                    (E[3] & E[2] & ~E[1] & E[0])   |
                    (E[3] & E[2] & E[1] & ~E[0]));


endmodule

src/codificador_tb.v
module codificador_tb ();

reg [3:0]E;
wire [2:0]S; 

//dump do sinal
initial begin
    $dumpfile("sim/codificador_tb.vcd"); 
    $dumpvars(0,codificador_tb);
end   

//instancia do codificador
codificador codificador1 (E,S);

//tabela verdade
initial begin
    E=10'd0; #10
    E=10'd1; #10
    E=10'd2; #10
    E=10'd3; #10
    E=10'd4; #10
    E=10'd5; #10
    E=10'd6; #10
    E=10'd7; #10
    E=10'd8; #10
    E=10'd9; #10
    E=10'd10; #10
    E=10'd11; #10
    E=10'd12; #10
    E=10'd13; #10
    E=10'd14; #10
    E=10'd15; #10

    $finish;
end   
endmodule

sim/codificador_tb.vcd
$date
	Fri Jun 19 09:34:20 2026
$end
$version
	Icarus Verilog
$end
$timescale
	1s
$end
$scope module codificador_tb $end
$var wire 3 ! S [2:0] $end
$var reg 4 " E [3:0] $end
$scope module codificador1 $end
$var wire 4 # E [3:0] $end
$var wire 3 $ S [2:0] $end
$upscope $end
$upscope $end
$enddefinitions $end
$comment Show the parameter values. $end
$dumpall
$end
#0
$dumpvars
b100 $
b0 #
b0 "
b100 !
$end
#10
b11 !
b11 $
b1 "
b1 #
#20
b11 !
b11 $
b10 "
b10 #
#30
b10 !
b10 $
b11 "
b11 #
#40
b11 !
b11 $
b100 "
b100 #
#50
b10 !
b10 $
b101 "
b101 #
#60
b10 !
b10 $
b110 "
b110 #
#70
b1 !
b1 $
b111 "
b111 #
#80
b11 !
b11 $
b1000 "
b1000 #
#90
b0 !
b0 $
b1001 "
b1001 #
#100
b10 !
b10 $
b1010 "
b1010 #
#110
b1 !
b1 $
b1011 "
b1011 #
#120
b10 !
b10 $
b1100 "
b1100 #
#130
b1 !
b1 $
b1101 "
b1101 #
#140
b1 !
b1 $
b1110 "
b1110 #
#150
b0 !
b0 $
b1111 "
b1111 #
