src/vaga.v
module vaga (
    input [3:0] E,
    output [1:0] S
);

// Configuração das saídas conforme o mapa de Karnaugh

// Configura a saída S1
assign S[1] = (E[1] & E[0]);

// Configura a saída S0
assign S[0] = ((~E[1] & E[0]) | (E[2] & E[1]));

endmodule

src/vaga_tb.v
module vaga_tb ();

reg [3:0]E;
wire [1:0]S; 

//dump do sinal
initial begin
    $dumpfile("sim/vaga_tb.vcd"); 
    $dumpvars(0,vaga_tb);
end   

//instancia do "vaga"
vaga vagae (E,S);

//tabela verdade
initial begin
    E=10'd0; #10
    E=10'd1; #10
    E=10'd2; #10
    E=10'd3; #10
    E=10'd4; #10
    E=10'd5; #10
    E=10'd6; #10
    E=10'd7; #10
    E=10'd8; #10
    E=10'd9; #10
    E=10'd10; #10
    E=10'd11; #10
    E=10'd12; #10
    E=10'd13; #10
    E=10'd14; #10
    E=10'd15; #10

    $finish;
end   
endmodule

sim/vaga_tb.vcd
$date
	Fri Jun 26 08:48:50 2026
$end
$version
	Icarus Verilog
$end
$timescale
	1s
$end
$scope module vaga_tb $end
$var wire 2 ! S [1:0] $end
$var reg 4 " E [3:0] $end
$scope module vagae $end
$var wire 4 # E [3:0] $end
$var wire 2 $ S [1:0] $end
$upscope $end
$upscope $end
$enddefinitions $end
$comment Show the parameter values. $end
$dumpall
$end
#0
$dumpvars
b0 $
b0 #
b0 "
b0 !
$end
#10
b1 !
b1 $
b1 "
b1 #
#20
b0 !
b0 $
b10 "
b10 #
#30
b10 !
b10 $
b11 "
b11 #
#40
b0 !
b0 $
b100 "
b100 #
#50
b1 !
b1 $
b101 "
b101 #
#60
b110 "
b110 #
#70
b11 !
b11 $
b111 "
b111 #
#80
b0 !
b0 $
b1000 "
b1000 #
#90
b1 !
b1 $
b1001 "
b1001 #
#100
b0 !
b0 $
b1010 "
b1010 #
#110
b10 !
b10 $
b1011 "
b1011 #
#120
b0 !
b0 $
b1100 "
b1100 #
#130
b1 !
b1 $
b1101 "
b1101 #
#140
b1110 "
b1110 #
#150
b11 !
b11 $
b1111 "
b1111 #
